{"status": "ok", "totalResults": 1, "articles": [{"source": {"id": "google-news", "name": "Google News"}, "author": "Pressing Your", "title": "Online affiliate marketing", "description": "Here's A Way To Earn 6-7 Figures A Month By Pressing Your Phone or Laptop And Getting Paid Every Friday", "url": "https://sites.google.com/view/afmwex/home", "urlToImage": "https://lh6.googleusercontent.com/cwS-ld02WudSU2Jp7aalu1MdszfQ98kMHit7yaSmyVDFjduityRMoWWv985YkdDKTavhJ8EpLh0pqXSOdeqrKRUTVEmDUxZYeR5Q91rnl_gZJjRGRI6cF-Lng3AGuapPEA=w1280", "publishedAt": "2021-08-15T08:52:44Z", "content": "My name is Ogbuji Christian, I assist individuals with building manageable online businesses in various enterprises, for example, e-commerce, affiliate marketing, and other business industries capabl\u2026 [+36 chars]"}]}