{"status": "ok", "totalResults": 1, "articles": [{"source": {"id": "google-news", "name": "Google News"}, "author": "Pinboard", "title": "Database connection closed after each request?", "description": null, "url": "https://groups.google.com/g/django-users/c/m1jeE4Cxr9A", "urlToImage": null, "publishedAt": "2021-08-13T17:45:46Z", "content": "&gt; Seen under this light, the additional 150ms latency resulting from non-&gt; persistent DB connection is huge - it implies almost 30% fewer&gt; customer orders. And it has nothing to do with traf\u2026 [+1687 chars]"}]}