{"status": "ok", "totalResults": 1, "articles": [{"source": {"id": null, "name": "Sporting News"}, "author": "Sporting News", "title": "La Juventus suspend trois de ses joueurs - Goal.com", "description": "Leicester City manager Brendan Rodgers was full of praise for Kelechi Iheanacho\u2019s personality after he signed contract extension that will keep him at the King Power Stadium until 2024.", "url": "https://www.sportingnews.com/ca/soccer", "urlToImage": "https://images.daznservices.com/di/library/sporting_news/a4/8/sportingnews_blid1xj976d41uqjx0jd6x52p.png", "publishedAt": "2021-04-02T19:24:44Z", "content": null}]}