{"status": "ok", "totalResults": 2, "articles": [{"source": {"id": null, "name": "Sporting News"}, "author": "Sporting News", "title": "Haaland r\u00e9pond aux rumeurs Manchester City et Barcelone - Goal.com", "description": "Thiago Alcantara doesn't understand why anyone would challenge the record of compatriot Sergio Busquets at Barcelona", "url": "https://www.sportingnews.com/ca/soccer", "urlToImage": "https://images.daznservices.com/di/library/sporting_news/a4/8/sportingnews_blid1xj976d41uqjx0jd6x52p.png", "publishedAt": "2021-03-23T10:40:51Z", "content": ""}]}